setup.py
src/digimat/__init__.py
src/digimat.vio.egg-info/PKG-INFO
src/digimat.vio.egg-info/SOURCES.txt
src/digimat.vio.egg-info/dependency_links.txt
src/digimat.vio.egg-info/namespace_packages.txt
src/digimat.vio.egg-info/not-zip-safe
src/digimat.vio.egg-info/requires.txt
src/digimat.vio.egg-info/top_level.txt
src/digimat/vio/__init__.py
src/digimat/vio/vio.py