Metadata-Version: 1.0
Name: digimat.vio
Version: 0.1.2
Summary: Digimat Managed VIO
Home-page: http://www.digimat.ch
Author: Frederic Hess
Author-email: fhess@splust.ch
License: PSF
Platform: UNKNOWN
